plover_space_config.py
plover_space_config-0.0.9.dist-info/LICENSE
plover_space_config-0.0.9.dist-info/METADATA
plover_space_config-0.0.9.dist-info/WHEEL
plover_space_config-0.0.9.dist-info/entry_points.txt
plover_space_config-0.0.9.dist-info/top_level.txt
plover_space_config-0.0.9.dist-info/zip-safe
plover_space_config-0.0.9.dist-info/RECORD
