Metadata-Version: 2.1
Name: plover-space-config
Version: 0.0.9
Summary: Plover command plugin for switching before/after spacing.
Home-page: https://github.com/pea/plover_space_config
Author: Ashlynn Anderson
Author-email: ashlynn.anderson@tutanota.com
License: GNU General Public License v3 or later (GPLv3+)
Keywords: plover plover_plugin
Platform: UNKNOWN
Classifier: Environment :: Plugins
Classifier: Intended Audience :: End Users/Desktop
Classifier: License :: OSI Approved :: GNU General Public License v3 or later (GPLv3+)
Classifier: Operating System :: OS Independent
Classifier: Programming Language :: Python :: 3
Classifier: Programming Language :: Python :: 3.6
Requires-Dist: plover (>=4.0.0.dev6)
